headfuck/__init__.py
headfuck/file.bf
headfuck/hff.py
headfuck/interpreter.py
headfuck/output_2023-04-17-19-29-24.txt
headfuck-2.0.dist-info/LICENSE
headfuck-2.0.dist-info/METADATA
headfuck-2.0.dist-info/WHEEL
headfuck-2.0.dist-info/entry_points.txt
headfuck-2.0.dist-info/RECORD
