Metadata-Version: 2.1
Name: headfuck
Version: 2.0
Summary: An esoteric programming language similar to Brainfuck
Author: JJPMaster
Author-email: joshuaponce2008@gmail.com
Requires-Python: >=3.10,<4.0
Classifier: License :: Public Domain
Classifier: Operating System :: OS Independent
Classifier: Programming Language :: Python :: 3
Classifier: Programming Language :: Python :: 3.10
Classifier: Programming Language :: Python :: 3.11
Classifier: Programming Language :: Python :: 3
